svdtools/VERSION
svdtools/__init__.py
svdtools/cli.py
svdtools/interrupts.py
svdtools/makedeps.py
svdtools/mmap.py
svdtools/patch.py
svdtools/test/__init__.py
svdtools/test/test_interrupts.py
svdtools/test/test_makedeps.py
svdtools/test/test_mmap.py
svdtools-0.1.27.dist-info/entry_points.txt
svdtools-0.1.27.dist-info/LICENSE-APACHE
svdtools-0.1.27.dist-info/LICENSE-MIT
svdtools-0.1.27.dist-info/WHEEL
svdtools-0.1.27.dist-info/METADATA
svdtools-0.1.27.dist-info/RECORD
