Metadata-Version: 2.1
Name: svdtools
Version: 0.1.27
Summary: svdpatch.py
Home-page: https://github.com/rust-embedded/svdtools
Author: Adam Greig
Author-email: adam@adamgreig.com
Maintainer: Nicolas Stalder
Maintainer-email: n@stalder.io
Requires-Python: >=3.9
Classifier: License :: OSI Approved :: MIT License
Classifier: License :: OSI Approved :: Apache Software License
Classifier: Intended Audience :: Developers
Classifier: Intended Audience :: End Users/Desktop
Classifier: Programming Language :: Python :: 3 :: Only
Classifier: Programming Language :: Python :: 3.9
Requires-Dist: click ~= 8.0
Requires-Dist: PyYAML >= 5.3, < 7
Requires-Dist: lxml ~= 4.6
Requires-Dist: braceexpand ~= 0.1.7
